Metadata-Version: 2.1
Name: plotar
Version: 0.8.3
Summary: Walk through your data
Home-page: https://github.com/thomann/plotAR 
Author: Philipp Thomann
Author-email: pht@gmx.ch
License: Affero GPL 3
Keywords: plotar
Platform: UNKNOWN
Classifier: Development Status :: 3 - Alpha
Classifier: Intended Audience :: Developers
Classifier: License :: OSI Approved :: GNU Affero General Public License v3
Classifier: Programming Language :: Python :: 3
Classifier: Programming Language :: Python :: 3.6
Classifier: Programming Language :: Python :: 3.7
Requires-Dist: pandas
Requires-Dist: numpy
Requires-Dist: requests
Requires-Dist: tornado
Requires-Dist: pyqrcode
Requires-Dist: click
Requires-Dist: usd-core
Requires-Dist: Pillow
Requires-Dist: jinja2
